README.md
setup.cfg
setup.py
dynamicmultithreadedexecutor/__init__.py
dynamicmultithreadedexecutor/dynamicmultithreadedexecutor.py
dynamicmultithreadedexecutor/exceptions.py
dynamicmultithreadedexecutor/finisher.py
dynamicmultithreadedexecutor/utils.py
dynamicmultithreadedexecutor/worker.py
dynamicmultithreadedexecutor.egg-info/PKG-INFO
dynamicmultithreadedexecutor.egg-info/SOURCES.txt
dynamicmultithreadedexecutor.egg-info/dependency_links.txt
dynamicmultithreadedexecutor.egg-info/requires.txt
dynamicmultithreadedexecutor.egg-info/top_level.txt