Metadata-Version: 1.1
Name: dynamicmultithreadedexecutor
Version: 1.0.2
Summary: Dynamic Multi-threaded Executor
Home-page: https://github.com/gumpcraca/dynamicmultithreadedexecutor
Author: Kevin McCabe
Author-email: csmp@hotmail.com
License: UNKNOWN
Download-URL: https://github.com/gumpcraca/dynamicmultithreadedexecutor/archive/1.0.2.zip
Platform: UNKNOWN
